django_deep_translator/__init__.py
django_deep_translator/compat.py
django_deep_translator/models.py
django_deep_translator/services.py
django_deep_translator/utils.py
django_deep_translator/management/__init__.py
django_deep_translator/management/commands/__init__.py
django_deep_translator/management/commands/translate_messages.py
django_deep_translator/tests/__init__.py
tests/__init__.py
django_deep_translator-1.5.1.dist-info/LICENSE
django_deep_translator-1.5.1.dist-info/METADATA
django_deep_translator-1.5.1.dist-info/WHEEL
django_deep_translator-1.5.1.dist-info/top_level.txt
django_deep_translator-1.5.1.dist-info/RECORD
