Metadata-Version: 2.1
Name: django-deep-translator
Version: 1.5.1
Summary: Automatically translate the pot (`.po`) files generated by django's makemessages command built on top of python deep-translator package
Home-page: https://github.com/wmo-raf/django-deep-translator
Author: Grace Amondi
Author-email: miswa.grace@gmail.com
License: MIT License
Classifier: Environment :: Web Environment
Classifier: Framework :: Django
Classifier: Development Status :: 5 - Production/Stable
Classifier: Intended Audience :: Developers
Classifier: License :: OSI Approved :: MIT License
Classifier: Natural Language :: English
Classifier: Programming Language :: Python
Classifier: Programming Language :: Python :: 3
Classifier: Topic :: Internet :: WWW/HTTP
Classifier: Topic :: Internet :: WWW/HTTP :: Dynamic Content
Classifier: Topic :: Software Development :: Libraries :: Python Modules
License-File: LICENSE
Requires-Dist: deep-translator >=1.10.1
Requires-Dist: django
Requires-Dist: polib
Requires-Dist: six
